Workbook

Sheet Supuestos
A1: CarsWiseAI — Modelo de unit economics multicanal
A2: Azul = input editable. Amarillo = placeholder a validar. Negro = fórmula. Verde = enlace entre hojas.
A4: Parámetro por canal | B4: C2C propio | C4: Feed dealer | D4: Importación | E4: Renting B2B | F4: Renting B2C | H4: Nota / origen
A5: Ticket medio del coche (€) | B5: 10000 | C5: 15000 | D5: 22000 | E5: 12500 | F5: 12500 | H5: Placeholder por canal
A6: Volumen transacciones / mes | B6: 30 | C6: 100 | D6: 5 | E6: 20 | F6: 10 | H6: PLACEHOLDER — a validar
A7: — INGRESOS —
A8: Fee inicio servicio (€) | B8: 150 | C8: 0 | D8: 0 | E8: 0 | F8: 0 | H8: Tu dato (150+150)
A9: Fee cierre servicio (€) | B9: 150 | C9: 0 | D9: 0 | E9: 0 | F9: 0 | H9: Tu dato
A10: % que cierra y tramita contigo | B10: 0.7 | C10: 1 | D10: 1 | E10: 1 | F10: 1 | H10: Placeholder (C2C)
A11: Margen sobre precio del coche (%) | B11: 0 | C11: 0 | D11: 0.1 | E11: 0.035 | F11: 0.08 | H11: Tu dato
A12: Lead fee / prescripción (€) | B12: 0 | C12: 175 | D12: 0 | E12: 0 | F12: 0 | H12: Tu dato (150-200)
A13: Attach financiación (%) | B13: 0.4 | C13: 0.2 | D13: 0.4 | E13: 0 | F13: 0.4 | H13: PLACEHOLDER (B2B=0)
A14: Attach garantía al comprador (%) | B14: 0.3 | C14: 0 | D14: 0 | E14: 0 | F14: 0 | H14: Dealer=0 (la da el dealer)
A15: — COSTES —
A16: Coste de servir / transacción (€) | B16: 45 | C16: 10 | D16: 350 | E16: 0 | F16: 0 | H16: C2C sin inspección; B2B/B2C en personal
A17: Peritación / verificación garantía (€) | B17: 0 | C17: 0 | D17: 200 | E17: 0 | F17: 200 | H17: Coste siempre (B2C)
A18: Forfait reparación si siniestro (€) | B18: 0 | C18: 0 | D18: 600 | E18: 0 | F18: 600 | H18: Tu dato (600)
A19: % siniestralidad (usa el forfait) | B19: 0 | C19: 0 | D19: 0.2 | E19: 0 | F19: 0.2 | H19: Tu dato (≈20%)
A20: CAC por transacción (€) | B20: 90 | C20: 0 | D20: 200 | E20: 0 | F20: 150 | H20: C2C=portal; dealer/B2B en fijos
A22: Parámetros transversales
A23: Comisión financiación (% s/ importe financiado) | B23: 0.075 | C23: Tu dato (7-8%)
A24: % del precio del coche que se financia | B24: 0.8 | C24: Placeholder
A25: Comisión por garantía vendida al comprador (€) | B25: 80 | C25: Mantener
A26: Prima media de seguro (€) | B26: 700 | C26: Tu dato · usado en hoja LTV
A27: % comisión sobre prima de seguro | B27: 0.08 | C27: Tu dato (mín. 8%) · LTV
A29: Costes fijos mensuales (€)
A30: Equipo (salarios + SS) | B30: 16000 | C30: PLACEHOLDER
A31: Plataforma, hosting y software | B31: 3000 | C31: PLACEHOLDER
A32: Legal, compliance y asesoría | B32: 2000 | C32: PLACEHOLDER
A33: Oficina y administración | B33: 2000 | C33: PLACEHOLDER
A34: Marca / marketing fijo (no CAC) | B34: 2000 | C34: PLACEHOLDER
A35: TOTAL costes fijos mensuales | B35: =SUM(B30:B34) -> 25000

Sheet Por canal
A1: Contribución por canal (transaccional, por unidad y mensual)
A3: Métrica | B3: C2C propio | C3: Feed dealer | D3: Importación | E3: Renting B2B | F3: Renting B2C | G3: TOTAL
A4: INGRESO POR UNIDAD
A5: Fee de servicio | B5: =Supuestos!B8+Supuestos!B10*Supuestos!B9 -> 255 | C5: =Supuestos!C8+Supuestos!C10*Supuestos!C9 -> 0 | D5: =Supuestos!D8+Supuestos!D10*Supuestos!D9 -> 0 | E5: =Supuestos!E8+Supuestos!E10*Supuestos!E9 -> 0 | F5: =Supuestos!F8+Supuestos!F10*Supuestos!F9 -> 0
A6: Margen sobre el coche | B6: =Supuestos!B5*Supuestos!B11 -> 0 | C6: =Supuestos!C5*Supuestos!C11 -> 0 | D6: =Supuestos!D5*Supuestos!D11 -> 2200 | E6: =Supuestos!E5*Supuestos!E11 -> 437.5 | F6: =Supuestos!F5*Supuestos!F11 -> 1000
A7: Lead fee / prescripción | B7: =Supuestos!B12 -> 0 | C7: =Supuestos!C12 -> 175 | D7: =Supuestos!D12 -> 0 | E7: =Supuestos!E12 -> 0 | F7: =Supuestos!F12 -> 0
A8: Comisión financiación | B8: =Supuestos!B13*Supuestos!$B$23*(Supuestos!B5*Supuestos!$B$24) -> 240 | C8: =Supuestos!C13*Supuestos!$B$23*(Supuestos!C5*Supuestos!$B$24) -> 180 | D8: =Supuestos!D13*Supuestos!$B$23*(Supuestos!D5*Supuestos!$B$24) -> 528 | E8: =Supuestos!E13*Supuestos!$B$23*(Supuestos!E5*Supuestos!$B$24) -> 0 | F8: =Supuestos!F13*Supuestos!$B$23*(Supuestos!F5*Supuestos!$B$24) -> 300
A9: Comisión garantía (ingreso) | B9: =Supuestos!B14*Supuestos!$B$25 -> 24 | C9: =Supuestos!C14*Supuestos!$B$25 -> 0 | D9: =Supuestos!D14*Supuestos!$B$25 -> 0 | E9: =Supuestos!E14*Supuestos!$B$25 -> 0 | F9: =Supuestos!F14*Supuestos!$B$25 -> 0
A10: Ingreso total / unidad | B10: =SUM(B5:B9) -> 519 | C10: =SUM(C5:C9) -> 355 | D10: =SUM(D5:D9) -> 2728 | E10: =SUM(E5:E9) -> 437.5 | F10: =SUM(F5:F9) -> 1300
A11: COSTE POR UNIDAD
A12: Coste de servir | B12: =Supuestos!B16 -> 45 | C12: =Supuestos!C16 -> 10 | D12: =Supuestos!D16 -> 350 | E12: =Supuestos!E16 -> 0 | F12: =Supuestos!F16 -> 0
A13: Coste garantía esperado | B13: =Supuestos!B17+Supuestos!B19*Supuestos!B18 -> 0 | C13: =Supuestos!C17+Supuestos!C19*Supuestos!C18 -> 0 | D13: =Supuestos!D17+Supuestos!D19*Supuestos!D18 -> 320 | E13: =Supuestos!E17+Supuestos!E19*Supuestos!E18 -> 0 | F13: =Supuestos!F17+Supuestos!F19*Supuestos!F18 -> 320
A14: Coste total / unidad | B14: =B12+B13 -> 45 | C14: =C12+C13 -> 10 | D14: =D12+D13 -> 670 | E14: =E12+E13 -> 0 | F14: =F12+F13 -> 320
A15: CONTRIBUCIÓN / UNIDAD | B15: =B10-B14 -> 474 | C15: =C10-C14 -> 345 | D15: =D10-D14 -> 2058 | E15: =E10-E14 -> 437.5 | F15: =F10-F14 -> 980
A16: CAC / unidad | B16: =Supuestos!B20 -> 90 | C16: =Supuestos!C20 -> 0 | D16: =Supuestos!D20 -> 200 | E16: =Supuestos!E20 -> 0 | F16: =Supuestos!F20 -> 150
A17: Contribución neta / unidad (tras CAC) | B17: =B15-B16 -> 384 | C17: =C15-C16 -> 345 | D17: =D15-D16 -> 1858 | E17: =E15-E16 -> 437.5 | F17: =F15-F16 -> 830
A18: Volumen / mes | B18: =Supuestos!B6 -> 30 | C18: =Supuestos!C6 -> 100 | D18: =Supuestos!D6 -> 5 | E18: =Supuestos!E6 -> 20 | F18: =Supuestos!F6 -> 10 | G18: =SUM(B18:F18) -> 165
A19: CONTRIBUCIÓN MENSUAL (tras CAC) | B19: =B17*B18 -> 11520 | C19: =C17*C18 -> 34500 | D19: =D17*D18 -> 9290 | E19: =E17*E18 -> 8750 | F19: =F17*F18 -> 8300 | G19: =SUM(B19:F19) -> 72360
A20: Ingreso mensual | B20: =B10*B18 -> 15570 | C20: =C10*C18 -> 35500 | D20: =D10*D18 -> 13640 | E20: =E10*E18 -> 8750 | F20: =F10*F18 -> 13000 | G20: =SUM(B20:F20) -> 86460

Sheet Viabilidad
A1: Viabilidad — P&L mensual y punto de equilibrio
A3: Foto mensual (a volumen base)
A4: Ingreso mensual total | B4: ='Por canal'!G20 -> 86460
A5: Contribución mensual total (tras CAC, antes de fijos) | B5: ='Por canal'!G19 -> 72360
A6: Costes fijos mensuales | B6: =Supuestos!B35 -> 25000
A7: EBITDA mensual | B7: =B5-B6 -> 47360
A8: Transacciones / mes | B8: ='Por canal'!G18 -> 165
A9: Contribución media / transacción (tras CAC) | B9: =B5/B8 -> 438.54545
A10: Break-even: transacciones/mes para cubrir fijos | B10: =B6/B9 -> 57.006633
A11: Holgura sobre break-even (transacciones) | B11: =B8-B10 -> 107.99337
A14: Rampa 12 meses (crecimiento de volumen hacia base)
A15: Arranque mes 1 (% del volumen base) | B15: 0.25
A16: Crecimiento mensual del volumen | B16: 0.18
A18: Mes | C18: 1 | D18: 2 | E18: 3 | F18: 4 | G18: 5 | H18: 6 | I18: 7 | J18: 8 | K18: 9 | L18: 10 | M18: 11 | N18: 12
A19: % del volumen base | C19: =$B$15 -> 0.25 | D19: =MIN(1,C19*(1+$B$16)) -> 0.295 | E19: =MIN(1,D19*(1+$B$16)) -> 0.3481 | F19: =MIN(1,E19*(1+$B$16)) -> 0.410758 | G19: =MIN(1,F19*(1+$B$16)) -> 0.48469444 | H19: =MIN(1,G19*(1+$B$16)) -> 0.57193944 | I19: =MIN(1,H19*(1+$B$16)) -> 0.67488854 | J19: =MIN(1,I19*(1+$B$16)) -> 0.79636848 | K19: =MIN(1,J19*(1+$B$16)) -> 0.9397148 | ... N19: =MIN(1,M19*(1+$B$16)) -> 1
A20: Transacciones / mes | C20: =C19*$B$8 -> 41.25 | D20: =D19*$B$8 -> 48.675 | E20: =E19*$B$8 -> 57.4365 | F20: =F19*$B$8 -> 67.77507 | G20: =G19*$B$8 -> 79.974583 | H20: =H19*$B$8 -> 94.370007 | I20: =I19*$B$8 -> 111.35661 | J20: =J19*$B$8 -> 131.4008 | ... N20: =N19*$B$8 -> 165
A21: Contribución (tras CAC) | C21: =C20*$B$9 -> 18090 | D21: =D20*$B$9 -> 21346.2 | E21: =E20*$B$9 -> 25188.516 | F21: =F20*$B$9 -> 29722.449 | G21: =G20*$B$9 -> 35072.49 | H21: =H20*$B$9 -> 41385.538 | I21: =I20*$B$9 -> 48834.935 | J21: =J20*$B$9 -> 57625.223 | ... N21: =N20*$B$9 -> 72360
A22: Costes fijos | C22: =$B$6 -> 25000 | D22: =$B$6 -> 25000 | E22: =$B$6 -> 25000 | F22: =$B$6 -> 25000 | G22: =$B$6 -> 25000 | H22: =$B$6 -> 25000 | I22: =$B$6 -> 25000 | J22: =$B$6 -> 25000 | ... N22: =$B$6 -> 25000
A23: EBITDA mensual | C23: =C21-C22 -> -6910 | D23: =D21-D22 -> -3653.8 | E23: =E21-E22 -> 188.516 | F23: =F21-F22 -> 4722.4489 | G23: =G21-G22 -> 10072.49 | H23: =H21-H22 -> 16385.538 | I23: =I21-I22 -> 23834.935 | J23: =J21-J22 -> 32625.223 | ... N23: =N21-N22 -> 47360
A24: EBITDA acumulado | C24: =C23 -> -6910 | D24: =C24+D23 -> -10563.8 | E24: =D24+E23 -> -10375.284 | F24: =E24+F23 -> -5652.8351 | G24: =F24+G23 -> 4419.6546 | H24: =G24+H23 -> 20805.192 | I24: =H24+I23 -> 44640.127 | J24: =I24+J23 -> 77265.35 | K24: =J24+K23 -> 120263.11 | ... N24: =M24+N23 -> 262343.11

Sheet LTV cliente
A1: Valor del cliente a lo largo de su vida (LTV) — por cliente captado
A2: Ingresos recurrentes (cartera) que la vista transaccional no ve. Todo ponderado por attach: por CLIENTE CAPTADO, no por contratante.
A4: Supuestos de cartera
A5: Horizonte de propiedad (años) | B5: 5 | C5: PLACEHOLDER
A6: Tasa de descuento anual | B6: 0.1 | C6: PLACEHOLDER
A7: Renovación anual del seguro | B7: 0.75 | C7: PLACEHOLDER — clave
A8: Retención anual de la relación (garaje activo) | B8: 0.8 | C8: PLACEHOLDER
A9: Probabilidad de recompra al final del horizonte | B9: 0.15 | C9: PLACEHOLDER — clave
A10: Contribución de la recompra (€) | B10: 390 | C10: ≈ contrib. neta C2C
A13: Productos de relación — margen esperado por cliente CAPTADO
A14: Producto | B14: Importe medio (€) | C14: % comisión | D14: Attach (%) | E14: Margen año 1 (€)
A15: Seguro (cartera) | B15: =Supuestos!B26 -> 700 | C15: =Supuestos!B27 -> 0.08 | D15: 0.2 | E15: =B15*C15*D15 -> 11.2
A16: Mantenimiento + neumáticos / año | B16: 450 | C16: 0.08 | D16: 0.2 | E16: =B16*C16*D16 -> 7.2
A17: ITV (cada 2 años) | B17: 60 | C17: 0.08 | D17: 0.2 | E17: =B17*C17*D17 -> 0.96
A20: Flujo recurrente por año (por cliente captado)
A21: Año | B21: 1 | C21: 2 | D21: 3 | E21: 4 | F21: 5
A22: Seguro | B22: =$E$15*($B$7^0) -> 11.2 | C22: =$E$15*($B$7^1) -> 8.4 | D22: =$E$15*($B$7^2) -> 6.3 | E22: =$E$15*($B$7^3) -> 4.725 | F22: =$E$15*($B$7^4) -> 3.54375
A23: Mantenimiento + neumáticos | B23: =$E$16*($B$8^0) -> 7.2 | C23: =$E$16*($B$8^1) -> 5.76 | D23: =$E$16*($B$8^2) -> 4.608 | E23: =$E$16*($B$8^3) -> 3.6864 | F23: =$E$16*($B$8^4) -> 2.94912
A24: ITV | B24: =IF(MOD(1,2)=0,$E$17*($B$8^0),0) -> 0 | C24: =IF(MOD(2,2)=0,$E$17*($B$8^1),0) -> 0.768 | D24: =IF(MOD(3,2)=0,$E$17*($B$8^2),0) -> 0 | E24: =IF(MOD(4,2)=0,$E$17*($B$8^3),0) -> 0.49152 | F24: =IF(MOD(5,2)=0,$E$17*($B$8^4),0) -> 0
A25: Flujo anual | B25: =B22+B23+B24 -> 18.4 | C25: =C22+C23+C24 -> 14.928 | D25: =D22+D23+D24 -> 10.908 | E25: =E22+E23+E24 -> 8.90292 | F25: =F22+F23+F24 -> 6.49287
A26: Factor de descuento | B26: =1/((1+$B$6)^1) -> 0.90909091 | C26: =1/((1+$B$6)^2) -> 0.82644628 | D26: =1/((1+$B$6)^3) -> 0.7513148 | E26: =1/((1+$B$6)^4) -> 0.68301346 | F26: =1/((1+$B$6)^5) -> 0.62092132
A27: Flujo descontado | B27: =B25*B26 -> 16.727273 | C27: =C25*C26 -> 12.33719 | D27: =D25*D26 -> 8.1953418 | E27: =E25*E26 -> 6.0808142 | F27: =F25*F26 -> 4.0315614
A30: Resultado
A31: VAN flujos recurrentes (seguro + mantenim. + ITV) | B31: =SUM(B27:F27) -> 47.37218
A32: + Recompra descontada (al final del horizonte) | B32: =B9*B10/((1+B6)^B5) -> 36.323897
A33: LTV por cliente captado (VAN) | B33: =B31+B32 -> 83.696078 | C33: Solo la cola recurrente; encima va la contribución transaccional (hoja Por canal).
A34: CAC de referencia (C2C) | B34: =Supuestos!B20 -> 90
A35: Ratio LTV recurrente / CAC | B35: =B33/B34 -> 0.92995642

Sheet Necesidad de capital
A1: Necesidad de capital — rampa hasta break-even y dilución
A2: 3 meses de arranque sin ventas (solo costes), primera venta el mes 4 y ~57/mes en el mes 18. Capital = caja más negativa.
A4: Supuestos de la ronda
A5: Meses de arranque sin ventas (solo costes) | B5: 3 | C5: Tu dato
A6: Arranque al empezar a vender (uds/mes) | B6: 15 | C6: Para llegar a 57/mes en mes 18
A7: Crecimiento mensual del volumen | B7: 0.1 | C7: Tu dato
A8: Contribución media / transacción (€) | B8: =Viabilidad!B9 -> 438.54545 | C8: Enlace
A9: Costes fijos mensuales (€) | B9: =Supuestos!B35 -> 25000 | C9: Enlace
A10: Break-even (unidades/mes) | B10: =B9/B8 -> 57.006633 | C10: Fórmula
A11: Colchón de seguridad (% sobre quema) | B11: 0.25 | C11: Placeholder
A13: Rampa mensual (24 meses)
A14: Mes | B14: 1 | C14: 2 | D14: 3 | E14: 4 | F14: 5 | G14: 6 | H14: 7 | I14: 8 | J14: 9 | K14: 10 | L14: 11 | M14: 12 | N14: 13 | O14: 14 | P14: 15 | Q14: 16 | R14: 17 | S14: 18 | T14: 19 | U14: 20 | V14: 21 | W14: 22 | X14: 23 | Y14: 24
A15: Unidades / mes | B15: =IF(1<=$B$5,0,$B$6*(1+$B$7)^(1-$B$5-1)) -> 0 | C15: =IF(2<=$B$5,0,$B$6*(1+$B$7)^(2-$B$5-1)) -> 0 | D15: =IF(3<=$B$5,0,$B$6*(1+$B$7)^(3-$B$5-1)) -> 0 | E15: =IF(4<=$B$5,0,$B$6*(1+$B$7)^(4-$B$5-1)) -> 15 | F15: =IF(5<=$B$5,0,$B$6*(1+$B$7)^(5-$B$5-1)) -> 16.5 | G15: =IF(6<=$B$5,0,$B$6*(1+$B$7)^(6-$B$5-1)) -> 18.15 | H15: =IF(7<=$B$5,0,$B$6*(1+$B$7)^(7-$B$5-1)) -> 19.965 | I15: =IF(8<=$B$5,0,$B$6*(1+$B$7)^(8-$B$5-1)) -> 21.9615 | J15: =IF(9<=$B$5,0,$B$6*(1+$B$7)^(9-$B$5-1)) -> 24.15765 | K15: =IF(10<=$B$5,0,$B$6*(1+$B$7)^(10-$B$5-1)) -> 26.573415 | L15: =IF(11<=$B$5,0,$B$6*(1+$B$7)^(11-$B$5-1)) -> 29.230756 | M15: =IF(12<=$B$5,0,$B$6*(1+$B$7)^(12-$B$5-1)) -> 32.153832 | N15: =IF(13<=$B$5,0,$B$6*(1+$B$7)^(13-$B$5-1)) -> 35.369215 | O15: =IF(14<=$B$5,0,$B$6*(1+$B$7)^(14-$B$5-1)) -> 38.906137 | P15: =IF(15<=$B$5,0,$B$6*(1+$B$7)^(15-$B$5-1)) -> 42.796751 | Q15: =IF(16<=$B$5,0,$B$6*(1+$B$7)^(16-$B$5-1)) -> 47.076426 | R15: =IF(17<=$B$5,0,$B$6*(1+$B$7)^(17-$B$5-1)) -> 51.784068 | S15: =IF(18<=$B$5,0,$B$6*(1+$B$7)^(18-$B$5-1)) -> 56.962475 | T15: =IF(19<=$B$5,0,$B$6*(1+$B$7)^(19-$B$5-1)) -> 62.658723 | U15: =IF(20<=$B$5,0,$B$6*(1+$B$7)^(20-$B$5-1)) -> 68.924595 | V15: =IF(21<=$B$5,0,$B$6*(1+$B$7)^(21-$B$5-1)) -> 75.817054 | W15: =IF(22<=$B$5,0,$B$6*(1+$B$7)^(22-$B$5-1)) -> 83.39876 | X15: =IF(23<=$B$5,0,$B$6*(1+$B$7)^(23-$B$5-1)) -> 91.738636 | Y15: =IF(24<=$B$5,0,$B$6*(1+$B$7)^(24-$B$5-1)) -> 100.9125
A16: Contribución | B16: =B15*$B$8 -> 0 | C16: =C15*$B$8 -> 0 | D16: =D15*$B$8 -> 0 | E16: =E15*$B$8 -> 6578.1818 | F16: =F15*$B$8 -> 7236 | G16: =G15*$B$8 -> 7959.6 | H16: =H15*$B$8 -> 8755.56 | I16: =I15*$B$8 -> 9631.116 | ... Y16: =Y15*$B$8 -> 44254.718
A17: Costes fijos | B17: =$B$9 -> 25000 | C17: =$B$9 -> 25000 | D17: =$B$9 -> 25000 | E17: =$B$9 -> 25000 | F17: =$B$9 -> 25000 | G17: =$B$9 -> 25000 | H17: =$B$9 -> 25000 | I17: =$B$9 -> 25000 | ... Y17: =$B$9 -> 25000
A18: EBITDA mensual | B18: =B16-B17 -> -25000 | C18: =C16-C17 -> -25000 | D18: =D16-D17 -> -25000 | E18: =E16-E17 -> -18421.818 | F18: =F16-F17 -> -17764 | G18: =G16-G17 -> -17040.4 | H18: =H16-H17 -> -16244.44 | I18: =I16-I17 -> -15368.884 | ... Y18: =Y16-Y17 -> 19254.718
A19: Caja acumulada | B19: =B18 -> -25000 | C19: =B19+C18 -> -50000 | D19: =C19+D18 -> -75000 | E19: =D19+E18 -> -93421.818 | F19: =E19+F18 -> -111185.82 | G19: =F19+G18 -> -128226.22 | H19: =G19+H18 -> -144470.66 | I19: =H19+I18 -> -159839.54 | J19: =I19+J18 -> -174245.31 | ... Y19: =X19+Y18 -> -178979.92
A22: Resultado
A23: Mes en que se alcanza el break-even (57/mes) | B23: =$B$5+ROUNDUP(LOG(B10/B6,1+B7),0)+1 -> 19
A24: Capital mínimo (caja más negativa) | B24: =-MIN(B19:Y19) -> 240994.84
A25: Capital recomendado (con colchón) | B25: =B24*(1+B11) -> 301243.55
A28: Dilución según valoración pre-money
A29: Escenario | B29: Pre-money (€) | C29: Capital (€) | D29: Post-money (€) | E29: % vendido
A30: Conservador | B30: 1000000 | C30: =$B$25 -> 301243.55 | D30: =B30+C30 -> 1301243.5 | E30: =C30/D30 -> 0.23150435
A31: Base | B31: 1750000 | C31: =$B$25 -> 301243.55 | D31: =B31+C31 -> 2051243.5 | E31: =C31/D31 -> 0.14685899
A32: Optimista | B32: 2500000 | C32: =$B$25 -> 301243.55 | D32: =B32+C32 -> 2801243.5 | E32: =C32/D32 -> 0.10753922

Sheet Agentes IA
A1: Agentes e IA en el proceso — impacto en escalabilidad
A2: La IA no es un adorno: mantiene plano el coste de servir y los fijos mientras crece el volumen. Eso es lo que hace escalable el núcleo.
A4: Proceso / línea | B4: Caso de uso (agente o modelo) | C4: Tipo | D4: Palanca en el modelo | E4: Escalab.
A5: Compra / recomendador | B5: Asesor conversacional que saca al comprador de la indecisión y recomienda el coche óptimo sobre tu inventario | C5: Agente | D5: Conversión↑ · CAC↓ · top de funnel | E5: Alta
A6: Venta C2C | B6: Tasación algorítmica con datos propietarios del garaje | C6: Modelo | D6: Producto + moat de datos | E6: Alta
A7: Venta C2C | B7: Generación de anuncios y mejora de fotos por portal | C7: Generativo | D7: Coste de servir C2C↓ | E7: Alta
A8: Venta C2C | B8: Filtro/cualificación de leads + agenda automática (Calendly) | C8: Agente | D8: Coste de servir C2C↓ (automatiza el filtro) | E8: Alta
A9: Financiación | B9: Matching multi-financiera y pre-cualificación del comprador | C9: Agente* | D9: Attach financiación↑ · conversión↑ | E9: Media
A10: Garaje digital | B10: OCR/visión de ITV, facturas y ficha técnica → autocompletar la ficha | C10: Modelo visión | D10: Coste de servir↓ · calidad de dato (moat) | E10: Alta
A11: Garaje digital | B11: Asistente proactivo de mantenimiento/ITV que ofrece la derivación al taller | C11: Agente | D11: Attach productos de relación↑ (LTV↑) | E11: Alta
A12: Importación | B12: Rastreo de listados en origen + cálculo de coste aterrizado (IEDMT) automático | C12: Agente | D12: Coste de servir importación↓ · sourcing | E12: Media
A13: Soporte / back-office | B13: Asistente de soporte + automatización de facturación y documentación | C13: Agente | D13: Costes fijos↓ · escalabilidad | E13: Alta
A15: * Línea roja: los agentes de financiación y seguros pueden pre-cualificar y comparar, pero el consejo y la decisión regulada exigen guardarraíles y humano en el bucle (crédito al consumo / DGSFP).
A17: Efecto neto: cada palanca "↓ coste de servir" o "↓ fijos" desplaza el break-even a la baja; cada "↑ attach" sube el LTV. La IA es lo que separa la curva de costes de la curva de volumen.
