Workbook

Sheet Resumen
A1: PopCar — Estructura de costes: importación de vehículos Alemania → España
A3: Este libro recoge, para cada partida de coste, las tablas oficiales/de referencia, las fórmulas de cálculo, las tarifas reales de vuestro proveedor de gestoría y las fuentes consultadas (sep. 2026). Incluye una hoja 'Simulador' para calcular el coste total de un vehículo concreto.
A6: Contenido del libro
A7: Hoja | B7: Contenido
A8: Simulador | B8: Calculadora del coste total de importación para un vehículo concreto (rellenar celdas amarillas).
A9: 1_Matriculacion | B9: IEDMT: tramos por CO2, coeficientes de depreciación, cómo se fija el valor base y qué CCAA aplica.
A10: 2_ITV_Homologacion | B10: Ficha técnica reducida + inspección ITV de matriculación en Aragón (cifras máximas, siempre COC válido).
A11: 3_Placas_Transferencia | B11: Tarifas REALES de vuestro proveedor de gestoría (gestión + tasa DGT + colegio) y placas físicas.
A12: 4_Transporte | B12: Transporte Alemania→Zaragoza (750€ real) y Zaragoza→destino final (fijo, 300€+IVA).
A13: Fuentes | B13: Listado de todas las fuentes consultadas, por partida.
A15: Novedades en esta versión (a partir de vuestro feedback)
A16: • IEDMT: se explica de dónde sale el valor que se deprecia (tablas Hacienda vs. factura de compra) y qué CCAA aplica.
A17: • ITV: se asume siempre COC válido (compráis así por norma) y se usan las cifras MÁXIMAS de cada rango, de cara a curarse en salud.
A18: • Placas/gestión: sustituidas las estimaciones públicas por la tabla de tarifas real de vuestro proveedor de gestoría.
A19: • Transporte Alemania→Zaragoza: sustituida la media orientativa por el coste real que os cobra el transportista (750€).
A21: Aviso importante
A22: Las tasas ITV y los precios de transporte de ejemplo proceden de blogs/comparadores (no siempre la fuente oficial primaria) y cambian cada año — confirmad los importes ITV vigentes con la estación de Zaragoza. El recargo autonómico del IEDMT en Aragón NO se ha podido confirmar con una fuente fiable (ver hoja 1_Matriculacion): preguntad a vuestro proveedor de gestoría, que lo aplica a diario.

Sheet Simulador
A1: SIMULADOR — COSTE TOTAL DE IMPORTACIÓN (ALEMANIA → ESPAÑA)
A2: Rellena las celdas amarillas (columna B) con los datos del vehículo. El resto se calcula solo.
A4: DATOS DEL VEHÍCULO Y DE LA OPERACIÓN
A5: Valor de mercado (tabla Hacienda) o precio de factura (€, sin IVA alemán) | B5: 25000
A6: Antigüedad del vehículo (años) | B6: 3
A7: Emisiones CO2 WLTP (g/km) | B7: 145
A8: Tipo de combustible (gasolina / diesel) | B8: gasolina
A9: ¿Aplicar recargo autonómico IEDMT +15%? (SI/NO) | B9: NO
A10: El valor de arriba es: TABLA (valor oficial Hacienda) o FACTURA (precio real de compra) | B10: FACTURA
A11: Ciudad de origen en Alemania (referencia) | B11: Múnich
A12: Coste real de transporte Alemania→Zaragoza (€, dejar en blanco = usar 750€ por defecto)
A13: Destino final del cliente en España | B13: Zaragoza ciudad
A15: 1. IMPUESTO DE MATRICULACIÓN (IEDMT)
A16: Coeficiente de depreciación (solo se usa si el valor es de TABLA) | B16: =INDEX('1_Matriculacion'!$C$21:$C$33,MATCH($B$6,'1_Matriculacion'!$A$21:$A$33,1)) -> 0.56
A17: Base imponible estimada (€) | B17: =IF($B$10="TABLA",$B$5*B16,$B$5) -> 25000
A18: Tipo impositivo aplicable (según CO2) | B18: =IF($B$9="SI",INDEX('1_Matriculacion'!$D$11:$D$14,MATCH($B$7,'1_Matriculacion'!$A$11:$A$14,1)),INDEX('1_Matriculacion'!$C$11:$C$14,MATCH($B$7,'1_Matriculacion'!$A$11:$A$14,1))) -> 0.0475
A19: Subtotal IEDMT (€) | B19: =B17*B18 -> 1187.5
A21: 2. ITV DE HOMOLOGACIÓN / MATRICULACIÓN (cifras máximas, COC siempre válido)
A22: Ficha técnica reducida (con IVA, valor máximo) | B22: ='2_ITV_Homologacion'!B12 -> 84.7
A23: Inspección ITV de matriculación (según combustible) | B23: =IF($B$8="diesel",'2_ITV_Homologacion'!B14,'2_ITV_Homologacion'!B13) -> 37.5
A24: Subtotal ITV homologación (€) | B24: =B22+B23 -> 122.2
A26: 3. GESTIÓN, TASA DGT Y PLACAS (tarifa real del proveedor)
A27: Gestión + tasa DGT + colegio (trámite: Transferencia — ver hoja 3 para alternativa con ITP) | B27: ='3_Placas_Transferencia'!E10 -> 83.6
A28: Placas de matrícula físicas (estimación, no incluida en tarifa proveedor) | B28: ='3_Placas_Transferencia'!B31 -> 24
A29: Subtotal gestión + placas (€) | B29: =B27+B28 -> 107.6
A31: 4. TRANSPORTE
A32: Tramo Alemania → Zaragoza (real si se indicó en B; si no, 750€ por defecto) | B32: =IF($B$12="",'4_Transporte'!B5,$B$12) -> 750
A33: Tramo Zaragoza → destino final (con IVA) | B33: ='4_Transporte'!B20 -> 363
A34: Subtotal transporte (€) | B34: =B32+B33 -> 1113
A36: COSTE TOTAL ESTIMADO DE IMPORTACIÓN (€) | B36: =B19+B24+B29+B34 -> 2530.3
A38: No incluye: IVA de compra del vehículo en Alemania (si aplica), impuesto de circulación anual (IVTM), honorarios de gestoría adicionales de PopCar, ni margen comercial. Estas partidas no se pidieron en el encargo original pero se pueden añadir como filas adicionales si se necesitan.

Sheet 1_Matriculacion
A1: IMPUESTO DE MATRICULACIÓN (IEDMT) — Modelo 576
A3: Fórmula: Impuesto = Base imponible × Tipo impositivo (según CO2 del vehículo)
A4: Base imponible (vehículo usado) = Valor de mercado × Coeficiente de depreciación por antigüedad — PERO el origen de ese 'valor de mercado' depende del caso: ver explicación más abajo.
A6: Fuente tramos CO2: RACE (race.es/impuesto-matriculacion-coche) y Agencia Tributaria (sede.agenciatributaria.gob.es).
A9: TABLA A — Tipos impositivos según emisiones de CO2 (turismos)
A10: CO2 desde (g/km, incl.) | B10: CO2 hasta (g/km, incl.) | C10: Tipo estatal | D10: Tipo con recargo autonómico máx. (+15%)
A11: 0 | B11: 120 | C11: 0 | D11: 0
A12: 121 | B12: 159 | C12: 0.0475 | D12: 0.054625
A13: 160 | B13: 199 | C13: 0.0975 | D13: 0.112125
A14: 200 | B14: ≥ 200 | C14: 0.1475 | D14: 0.169625
A15: Las Comunidades Autónomas pueden incrementar los tipos estatales hasta un 15%. La columna D es el MÁXIMO legal posible, no necesariamente lo que aplica Aragón hoy (ver aviso más abajo).
A16: Tramo 0% incluye vehículos eléctricos puros y determinados híbridos enchufables/autónomos de largo alcance según normativa vigente.
A19: TABLA B — Coeficientes de depreciación por antigüedad (solo aplicable al 'Camino 1', ver más abajo)
A20: Antigüedad desde (años, incl.) | B20: Antigüedad hasta (años, excl.) | C20: % del valor
A21: 0 | B21: 1 | C21: 1
A22: 1 | B22: 2 | C22: 0.84
A23: 2 | B23: 3 | C23: 0.67
A24: 3 | B24: 4 | C24: 0.56
A25: 4 | B25: 5 | C25: 0.47
A26: 5 | B26: 6 | C26: 0.39
A27: 6 | B27: 7 | C27: 0.34
A28: 7 | B28: 8 | C28: 0.28
A29: 8 | B29: 9 | C29: 0.24
A30: 9 | B30: 10 | C30: 0.19
A31: 10 | B31: 11 | C31: 0.17
A32: 11 | B32: 12 | C32: 0.13
A33: 12 | B33: > 12 | C33: 0.1
A34: Fuente: tablas de coeficientes de depreciación de Hacienda para valoración fiscal de vehículos usados (aplicables a IEDMT e ITP).
A37: ¿DE DÓNDE SALE EL VALOR QUE SE DEPRECIA? (respuesta a vuestra pregunta)
A38: El 'valor de mercado' NO es, en general, el precio de venta cuando el coche era nuevo: es uno de estos dos valores, según el caso — y son excluyentes entre sí (no se depreciar dos veces).
A39: CAMINO 1 — El modelo/versión concreto está en las tablas oficiales de valoración que Hacienda aprueba cada año (Orden HAC, p.ej. Orden HAC/1501/2025 para 2026, BOE): se toma el valor de esa tabla para ese modelo/año y SE LE APLICA la Tabla B (coeficiente por antigüedad).
A40: CAMINO 2 — El modelo/versión NO está en esas tablas (muy habitual en versiones de mercado alemán que nunca se comercializaron oficialmente en España): se declara directamente el valor de mercado real del vehículo — normalmente el precio de la factura de compra — SIN aplicar depreciación adicional. La factura de un coche usado ya refleja su valor actual; volver a depreciarla infravaloraría la base imponible. Hacienda puede comprobar el valor si lo considera anormalmente bajo.
A41: En la práctica de importación de coches alemanes de versión no vendida en España, el Camino 2 (factura real) es el más habitual.
A42: Fuente: instrucciones del Modelo 576 (Agencia Tributaria) y Orden HAC/1501/2025 (BOE) de precios medios de venta.
A44: ¿QUÉ COMUNIDAD AUTÓNOMA APLICA? (respuesta a vuestra pregunta)
A45: El tipo (incluido el posible recargo de la columna D) es, en principio, el de la Comunidad Autónoma del DOMICILIO FISCAL REAL del titular que matricula el vehículo (su empadronamiento) — no el de la comunidad donde a PopCar le interese matricular. La normativa de cesión de tributos vincula el impuesto al domicilio fiscal real del sujeto pasivo.
A46: Matricular en una provincia/CCAA distinta de la residencia real del cliente para pagar menos, y cambiar después el domicilio en el permiso de circulación, es una práctica de riesgo fiscal (análoga a las 'banderas de conveniencia' que Hacienda persigue en el IVTM): si se detecta que el domicilio declarado no era el real en el momento de matricular, la Administración puede exigir la diferencia de impuesto, con recargos e intereses. Esto no es asesoramiento legal — consultad con un abogado/asesor fiscal antes de adoptar esta práctica como política de empresa.
A47: Recomendación práctica: matricular siempre con el domicilio fiscal real del cliente final (donde vaya a estar domiciliado el vehículo).
A48: No hemos podido confirmar con una fuente pública fiable si Aragón tiene hoy un recargo autonómico aprobado sobre el tipo estatal del IEDMT. Vía más rápida y fiable: preguntad directamente a vuestro proveedor de gestoría (el de la tabla de tarifas de la hoja 3) — lo aplican a diario. Alternativa oficial: Agencia Tributaria de Aragón.

Sheet 2_ITV_Homologacion
A1: ITV DE HOMOLOGACIÓN / MATRICULACIÓN — VEHÍCULO IMPORTADO UE (ALEMANIA)
A3: Asunción de negocio: todos los vehículos se compran con Certificado de Conformidad (COC) europeo válido. Por tanto, NO se necesita homologación individual (ese trámite, de 1.500-3.500€, solo aplica a vehículos sin homologación europea — procedencia extra-UE o reformas no homologadas — y no debería daros nunca con vuestro modelo de compra).
A5: Para curarse en salud, se usa el valor MÁXIMO de cada rango de mercado (no la media), de forma que el coste real nunca debería superar la estimación.
A8: TABLA — Costes ITV / homologación (vehículo con COC válido)
A9: Concepto | B9: Coste (€) | C9: Fuente / nota
A10: Ficha técnica reducida (turismo/furgoneta), base sin IVA — valor MÁXIMO de mercado | B10: 70 | C10: Rango de mercado 45-70€+IVA (ingeniauto.es). Se usa el máximo (70€) a propósito.
A11: IVA sobre ficha reducida (21%) | B11: =B10*0.21 -> 14.7
A12: Ficha técnica reducida, total con IVA | B12: =B10+B11 -> 84.7
A13: Inspección ITV de matriculación — turismo GASOLINA (Aragón, 2026) | B13: 37.5 | C13: Tarifas ITV Aragón 2026 (atarvez.com) — verificar tarifa oficial en itv.es
A14: Inspección ITV de matriculación — turismo DIÉSEL (Aragón, 2026) | B14: 46.76 | C14: Tarifas ITV Aragón 2026 (atarvez.com) — verificar tarifa oficial en itv.es
A16: COSTE TOTAL ITV homologación — GASOLINA (€, máximo) | B16: =B12+B13 -> 122.2
A17: COSTE TOTAL ITV homologación — DIÉSEL (€, máximo) | B17: =B12+B14 -> 131.46
A20: Referencia (NO aplica a vuestro modelo de compra — solo si algún día comprarais un vehículo SIN COC válido): homologación individual completa 1.500-3.500€; sustitución de COC extraviado 300-800€ (needcarhelp.es).
A22: Recomendación: confirmar con la estación ITV de Zaragoza el importe exacto vigente y si el modelo concreto está ya en su base de datos (algunos vehículos recientes no requieren ficha reducida).

Sheet 3_Placas_Transferencia
A1: GESTIÓN, TASAS DGT Y PLACAS — TARIFAS REALES DE VUESTRO PROVEEDOR
A3: Al importar de Alemania, el trámite en DGT es una matriculación/alta de titularidad a nombre del cliente final — no una transferencia entre dos titulares ya matriculados en España. Vuestro proveedor factura este tipo de trámite bajo las tarifas de 'transferencia' de esta tabla (tal como nos habéis indicado), por lo que se ha tomado como fila por defecto la de TRANSFERENCIAS.
A5: Supuesto por defecto: compra con factura de un vendedor profesional en Alemania (sin ITP). Si en algún caso concreto compráis a un particular alemán y aplica ITP/Modelo 620, usad manualmente la fila 'TRANSFERENCIA CON ITP O MODELO 620' en el Simulador.
A8: Tarifario proveedor (gestión + tasa DGT + cuota colegio de gestores)
A9: Concepto | B9: Gestión (€) | C9: Tasa DGT (€) | D9: Colegio (€) | E9: TOTAL (€) | F9: Nota
A10: TRANSFERENCIAS | B10: 20 | C10: 55.7 | D10: 7.9 | E10: =B10+C10+D10 -> 83.6 | F10: Fila usada por defecto en el Simulador (importación con factura de profesional).
A11: TRANSFERENCIA CON ITP O MODELO 620 | B11: 25 | C11: 55.7 | D11: 7.9 | E11: =B11+C11+D11 -> 88.6 | F11: Usar si la compra es a un particular y aplica ITP/Modelo 620.
A12: TRANSFERENCIA Y NOTIFICACIÓN DE TRANSMISIÓN O VICEVERSA | B12: 30 | C12: 64.37 | D12: 10.85 | E12: =B12+C12+D12 -> 105.22
A13: INFORME DE TRÁFICO | B13: 3 | C13: 8.67 | D13: 1.65 | E13: =B13+C13+D13 -> 13.32
A14: BAJA TRÁNSITO COMUNITARIO / EXPORTACIÓN / TEMPORAL, ETC. | B14: 15 | C14: 8.67 | D14: 2.95 | E14: =B14+C14+D14 -> 26.62
A15: DUPLICADO PERMISO DE CIRCULACIÓN | B15: 12 | C15: 20.81 | D15: 3.2 | E15: =B15+C15+D15 -> 36.01
A16: DUPLICADO FICHA TÉCNICA ELECTRÓNICA | B16: 12 | C16: 8.67 | D16: 3.2 | E16: =B16+C16+D16 -> 23.87
A17: BAJA TEMPORAL POR ENTREGA A COMPRAVENTA | B17: 12 | C17: 8.67 | D17: 2.95 | E17: =B17+C17+D17 -> 23.62
A19: Otras tarifas del proveedor sin importe fijo (coste variable 'según gestión')
A20: Concepto | B20: Gestión (€) | C20: Tasa DGT | D20: Colegio | F20: Nota
A21: SOLICITAR Y RECOGER CARTA FINANCIERA Y CANCELAR EN REGISTRO | B21: 24 | C21: Según gestión | D21: —
A22: CRD EN REGISTRO | B22: 12 | C22: Según gestión | D22: —
A23: CAMBIO DOMICILIO EN PERMISO DE CIRCULACIÓN | B23: 9 | C23: — | D23: 3,20€ colegio
A24: IMPUESTO VEHÍCULOS TRACCIÓN MECÁNICA (V.O.) MADRID/PUEBLOS | B24: 18 | C24: Según IVTM | D24: —
A25: CONSULTAS MULTAS TESTRA O DGT | B25: 3 | C25: Según gestión | D25: —
A26: CAMBIO DE SERVICIO EN FT (ITV), TASA INDUSTRIA | B26: 15 | C26: 35,00€ | D26: —
A27: CAMBIO DE SERVICIO EN PC URGENTE (24-48h) | B27: 70 | C27: — | D27: —
A29: Placas físicas de matrícula (no incluidas en la tarifa del proveedor)
A30: Concepto | B30: Coste (€) | F30: Nota
A31: Placas de matrícula físicas nuevas (juego delantera+trasera) | B31: 24 | F31: Estimación pública (18-30€, tramitesvehiculo.es) — vuestro proveedor no lo incluye en su tarifario; confirmar coste real con el proveedor de placas.
A33: COSTE TOTAL matriculación/transferencia (proveedor) + placas (€) | B33: =E10+B31 -> 107.6

Sheet 4_Transporte
A1: TRANSPORTE DEL VEHÍCULO
A3: Tramo 1 — Alemania → Zaragoza (ITV y puesta a punto)
A4: Concepto | B4: Coste (€) | C4: Fuente / nota
A5: Coste real acordado con vuestro transportista habitual | B5: 750 | C5: Dato real proporcionado por PopCar (sep. 2026). Valor usado por defecto en el Simulador.
A7: Referencia de mercado (para contrastar el precio anterior)
A8: Ruta de ejemplo | B8: Coste aprox. (€) | C8: Fuente
A9: Múnich → Madrid | B9: 950 | C9: caralyze.es
A10: Hamburgo → Barcelona | B10: 1050 | C10: caralyze.es
A11: Frankfurt → Sevilla | B11: 1000 | C11: caralyze.es
A12: Rango general observado Alemania → España | B12: 400 - 1.100 | C12: eurotransportcar.com
A14: Los 750€ reales que os cobra vuestro transportista están dentro/por debajo del rango de mercado observado, así que parece un precio razonable. Si cambiáis de transportista o de zona habitual de origen en Alemania, actualizad la celda B5 de esta hoja.
A16: Tramo 2 — Zaragoza → destino final del cliente (coste fijo con margen)
A17: Concepto | B17: Coste (€) | C17: Fuente / nota
A18: Coste base tramo Zaragoza → destino (sin IVA) | B18: 300 | C18: Dato interno PopCar: importe fijo estimado con margen/colchón, independiente del destino en península.
A19: IVA (21%) | B19: =B18*0.21 -> 63
A20: COSTE TOTAL tramo Zaragoza → destino final (con IVA) | B20: =B18+B19 -> 363

Sheet Fuentes
A1: FUENTES CONSULTADAS
A3: Partida | B3: Fuente | C3: URL
A4: IEDMT - tramos CO2 | B4: RACE | C4: https://www.race.es/impuesto-matriculacion-coche
A5: IEDMT - tramos CO2 / normativa | B5: Agencia Tributaria | C5: https://sede.agenciatributaria.gob.es/Sede/impuestos-tasas/impuesto-matriculacion.html
A6: IEDMT - depreciación por antigüedad | B6: noticias.coches.com | C6: https://noticias.coches.com/consejos/valor-hacienda-coche/399888
A7: IEDMT - base imponible (Modelo 576) | B7: Agencia Tributaria - Instrucciones | C7: https://sede.agenciatributaria.gob.es/Sede/todas-gestiones/impuestos-tasas/impuesto-matriculacion/modelo-576-impue_____eterminados-medios-transporte-autoliquidacion_/instrucciones.html
A8: IEDMT - precios medios de venta 2026 | B8: BOE - Orden HAC/1501/2025 | C8: https://www.boe.es/diario_boe/txt.php?id=BOE-A-2025-26357
A9: IEDMT - base imponible / CCAA aplicable | B9: RO-DES | C9: https://www.ro-des.com/info/dgt/impuesto-de-matriculacion-de-coches/
A10: IEDMT - domicilio fiscal / provincia de matriculación | B10: MatricularCoches.com | C10: https://www.matricularcoches.com/como-elegir-la-provincia-y-municipio-fiscal-para-matricular-un-vehiculo-si-tienes-mas-de-una-residencia-guia/
A11: Matriculación vehículo procedente de la UE | B11: DGT | C11: https://www.dgt.es/nuestros-servicios/tu-vehiculo/quieres-traer-o-llevarte-un-vehiculo-del-extranjero/matricular-un-vehiculo-proveniente-de-la-ue/
A12: Ficha técnica reducida - precio | B12: Ingeniauto | C12: https://ingeniauto.es/ficha-tecnica-reducida/precio-ficha-tecnica-reducida/
A13: Homologación individual / COC / importación | B13: NeedCarHelp | C13: https://needcarhelp.es/blog/importar-coche-alemania/
A14: Tarifas ITV Aragón 2026 | B14: Atarvez | C14: https://atarvez.com/nuevas-tarifas-itv-aragon-2026/
... A19: Transporte Alemania-Zaragoza, coste real | B19: Transportista habitual de PopCar (dato interno) | C19: —
